classic/composites/__init__.py
classic/composites/namespace.py
classic/composites/wrappers.py
classic_composites-0.0.1.dist-info/licenses/LICENSE
classic_composites-0.0.1.dist-info/METADATA
classic_composites-0.0.1.dist-info/WHEEL
classic_composites-0.0.1.dist-info/top_level.txt
classic_composites-0.0.1.dist-info/RECORD
